kay_pi_de_toolkit/__init__.py
kay_pi_de_toolkit/main.py
kay_pi_de_toolkit/vm.py
kay_pi_de_toolkit-0.1.0.dist-info/METADATA
kay_pi_de_toolkit-0.1.0.dist-info/WHEEL
kay_pi_de_toolkit-0.1.0.dist-info/entry_points.txt
kay_pi_de_toolkit-0.1.0.dist-info/RECORD
